{
    "1": {
        "id": 1,
        "category_id": 3,
        "title": "Путешествие в Токио",
        "text": "Посещение......",
        "created_at": "2025-11-11 00:57:24"
    },
    "2": {
        "id": 2,
        "category_id": 5,
        "title": "Нью-Йорк",
        "text": "Каникулы.....",
        "created_at": "2025-11-14 21:30:29"
    },
    "3": {
        "title": "яввфв",
        "category_id": "1",
        "text": "выЫыссыяысы",
        "id": 3,
        "created_at": "2025-11-20 03:28:40"
    },
    "4": {
        "title": "яввфв",
        "category_id": "1",
        "text": "выЫыссыяысы",
        "id": 4,
        "created_at": "2025-11-20 03:28:48"
    },
    "5": {
        "title": "счяч",
        "category_id": "1",
        "text": "Всвсвсвсвсв",
        "id": 5,
        "created_at": "2025-11-20 03:29:01"
    },
    "6": {
        "title": "счяч",
        "category_id": "1",
        "text": "Всвсвсвсвсв",
        "id": 6,
        "created_at": "2025-11-20 03:31:10"
    }
}